CHANGES.txt
MANIFEST.in
README.md
README.rst
message-extraction.ini
setup.cfg
setup.py
pyramid_admin/__init__.py
pyramid_admin/filters.py
pyramid_admin/forms.py
pyramid_admin/interfaces.py
pyramid_admin/site.py
pyramid_admin/utils.py
pyramid_admin/views.py
pyramid_admin.egg-info/PKG-INFO
pyramid_admin.egg-info/SOURCES.txt
pyramid_admin.egg-info/dependency_links.txt
pyramid_admin.egg-info/not-zip-safe
pyramid_admin.egg-info/paster_plugins.txt
pyramid_admin.egg-info/requires.txt
pyramid_admin.egg-info/top_level.txt
pyramid_admin/assets/jquery.min.js
pyramid_admin/assets/css/admin.css
pyramid_admin/assets/css/bootstrap-responsive.css
pyramid_admin/assets/css/bootstrap-responsive.min.css
pyramid_admin/assets/css/bootstrap.css
pyramid_admin/assets/css/bootstrap.min.css
pyramid_admin/assets/css/chosen-sprite.png
pyramid_admin/assets/css/chosen.css
pyramid_admin/assets/css/jquery-ui.css
pyramid_admin/assets/css/images/ui-bg_flat_0_aaaaaa_40x100.png
pyramid_admin/assets/css/images/ui-bg_flat_75_ffffff_40x100.png
pyramid_admin/assets/css/images/ui-bg_glass_55_fbf9ee_1x400.png
pyramid_admin/assets/css/images/ui-bg_glass_65_ffffff_1x400.png
pyramid_admin/assets/css/images/ui-bg_glass_75_dadada_1x400.png
pyramid_admin/assets/css/images/ui-bg_glass_75_e6e6e6_1x400.png
pyramid_admin/assets/css/images/ui-bg_glass_95_fef1ec_1x400.png
pyramid_admin/assets/css/images/ui-bg_highlight-soft_75_cccccc_1x100.png
pyramid_admin/assets/css/images/ui-icons_222222_256x240.png
pyramid_admin/assets/css/images/ui-icons_2e83ff_256x240.png
pyramid_admin/assets/css/images/ui-icons_454545_256x240.png
pyramid_admin/assets/css/images/ui-icons_888888_256x240.png
pyramid_admin/assets/css/images/ui-icons_cd0a0a_256x240.png
pyramid_admin/assets/img/glyphicons-halflings-white.png
pyramid_admin/assets/img/glyphicons-halflings.png
pyramid_admin/assets/js/bootstrap.js
pyramid_admin/assets/js/bootstrap.min.js
pyramid_admin/assets/js/chosen.jquery.min.js
pyramid_admin/assets/js/jquery-ui.min.js
pyramid_admin/locale/ru/LC_MESSAGES/pyramid_admin.mo
pyramid_admin/templates/base.jinja2
pyramid_admin/templates/confirm_delete.jinja2
pyramid_admin/templates/edit.jinja2
pyramid_admin/templates/index.jinja2
pyramid_admin/templates/layout.jinja2
